LICENSE
README.rst
setup.py
executor/__init__.py
executor/constant.py
executor/core.py
executor/engine.py
executor/init_import.py
executor/log_support.py
executor/pooling.py
executor/sql_support.py
executor/support.py
sqlx_executor.egg-info/PKG-INFO
sqlx_executor.egg-info/SOURCES.txt
sqlx_executor.egg-info/dependency_links.txt
sqlx_executor.egg-info/not-zip-safe
sqlx_executor.egg-info/top_level.txt